athena/__init__.py
athena/athena.py
athena/labels2d.py
athena/logo.png
athena/montage.py
athena/triangulaterefine.py
athena/models/hand_landmarker.task
athena/models/pose_landmarker_full.task
athena_tracking-0.9.dist-info/licenses/LICENSE
athena_tracking-0.9.dist-info/METADATA
athena_tracking-0.9.dist-info/WHEEL
athena_tracking-0.9.dist-info/entry_points.txt
athena_tracking-0.9.dist-info/top_level.txt
athena_tracking-0.9.dist-info/RECORD
