Metadata-Version: 2.4
Name: athena-tracking
Version: 0.9
Summary: ATHENA: Automatically Tracking Hands Expertly with No Annotations
Author-email: Jonathan Michaels <jmichae@yorku.ca>, Daanish Mulla <daanish.mulla@gmail.com>
Project-URL: GitHub, https://github.com/neural-control-and-computation-lab/athena
Keywords: athena,hand tracking,pose estimation,machine learning
Classifier: Development Status :: 4 - Beta
Classifier: Programming Language :: Python :: 3.12
Classifier: License :: OSI Approved :: MIT License
Classifier: Operating System :: OS Independent
Requires-Python: ==3.12.*
License-File: LICENSE
Requires-Dist: av
Requires-Dist: mediapipe
Requires-Dist: numpy
Requires-Dist: matplotlib
Requires-Dist: tqdm
Requires-Dist: scipy
Requires-Dist: pymovie
Requires-Dist: toml
Requires-Dist: moviepy
Dynamic: license-file
